spaceone/__init__.py
spaceone/inventory/__init__.py
spaceone/inventory/conf/__init__.py
spaceone/inventory/conf/collector_conf.py
spaceone/inventory/conf/global_conf.py
spaceone/inventory/connector/__init__.py
spaceone/inventory/connector/file_upload_connector.py
spaceone/inventory/connector/smtp_connector.py
spaceone/inventory/error/__init__.py
spaceone/inventory/error/cloud_service_query_set.py
spaceone/inventory/error/cloud_service_stats.py
spaceone/inventory/error/cloud_service_type.py
spaceone/inventory/error/collect_data.py
spaceone/inventory/error/collector.py
spaceone/inventory/error/collector_rule.py
spaceone/inventory/error/export.py
spaceone/inventory/error/file_upload.py
spaceone/inventory/error/region.py
spaceone/inventory/error/server.py
spaceone/inventory/error/smtp.py
spaceone/inventory/info/__init__.py
spaceone/inventory/info/change_history_info.py
spaceone/inventory/info/cloud_service_info.py
spaceone/inventory/info/cloud_service_query_set_info.py
spaceone/inventory/info/cloud_service_report_info.py
spaceone/inventory/info/cloud_service_stats_info.py
spaceone/inventory/info/cloud_service_type_info.py
spaceone/inventory/info/collector_info.py
spaceone/inventory/info/collector_rule_info.py
spaceone/inventory/info/common_info.py
spaceone/inventory/info/job_info.py
spaceone/inventory/info/job_task_info.py
spaceone/inventory/info/note_info.py
spaceone/inventory/info/region_info.py
spaceone/inventory/interface/__init__.py
spaceone/inventory/interface/grpc/__init__.py
spaceone/inventory/interface/grpc/change_history.py
spaceone/inventory/interface/grpc/cloud_service.py
spaceone/inventory/interface/grpc/cloud_service_query_set.py
spaceone/inventory/interface/grpc/cloud_service_report.py
spaceone/inventory/interface/grpc/cloud_service_stats.py
spaceone/inventory/interface/grpc/cloud_service_type.py
spaceone/inventory/interface/grpc/collector.py
spaceone/inventory/interface/grpc/collector_rule.py
spaceone/inventory/interface/grpc/job.py
spaceone_inventory-2.0.40.dist-info/METADATA
spaceone_inventory-2.0.40.dist-info/WHEEL
spaceone_inventory-2.0.40.dist-info/top_level.txt
spaceone_inventory-2.0.40.dist-info/RECORD
