Metadata-Version: 2.1
Name: spaceone-inventory
Version: 2.0.40
Summary: SpaceONE inventory service
Home-page: https://www.spaceone.dev/
Author: MEGAZONE SpaceONE Team
Author-email: admin@spaceone.dev
License: Apache License 2.0
Platform: UNKNOWN
Requires-Dist: spaceone-core
Requires-Dist: spaceone-api
Requires-Dist: langcodes
Requires-Dist: ipaddress
Requires-Dist: fakeredis
Requires-Dist: pandas
Requires-Dist: jinja2
Requires-Dist: openpyxl
Requires-Dist: pytz
